autometa/__init__.py
autometa/api.py
autometa/autometa.py
autometa/util.py
autometa-0.3.0.dist-info/AUTHORS.rst
autometa-0.3.0.dist-info/LICENSE
autometa-0.3.0.dist-info/METADATA
autometa-0.3.0.dist-info/WHEEL
autometa-0.3.0.dist-info/top_level.txt
autometa-0.3.0.dist-info/RECORD
