Metadata-Version: 2.1
Name: autometa
Version: 0.3.0
Summary: autometa library prototype
Author-email: Carlos Corral-Williams <c0rwil@protonmail.com>
Classifier: Programming Language :: Python :: 3
Classifier: License :: OSI Approved :: MIT License
Classifier: Operating System :: OS Independent
Requires-Python: >=3.10
License-File: LICENSE
License-File: AUTHORS.rst
Requires-Dist: build
Requires-Dist: setuptools
Requires-Dist: toml
Requires-Dist: pyyaml
